wrapx/__init__.py
wrapx-0.0.1.dist-info/licenses/LICENSE
wrapx-0.0.1.dist-info/METADATA
wrapx-0.0.1.dist-info/WHEEL
wrapx-0.0.1.dist-info/top_level.txt
wrapx-0.0.1.dist-info/RECORD
