Metadata-Version: 2.4
Name: wrapx
Version: 0.0.1
Summary: Standardized API response envelopes using Pydantic
Author: Til Schwarze
License: MIT
Requires-Python: >=3.9
License-File: LICENSE
Requires-Dist: pydantic>=2.0
Dynamic: author
Dynamic: description-content-type
Dynamic: license
Dynamic: license-file
Dynamic: requires-dist
Dynamic: requires-python
Dynamic: summary
